CHANGES.txt
LICENSE.txt
MANIFEST.in
README.txt
setup.py
js/__init__.py
js.jquery_expandbox.egg-info/PKG-INFO
js.jquery_expandbox.egg-info/SOURCES.txt
js.jquery_expandbox.egg-info/dependency_links.txt
js.jquery_expandbox.egg-info/entry_points.txt
js.jquery_expandbox.egg-info/namespace_packages.txt
js.jquery_expandbox.egg-info/not-zip-safe
js.jquery_expandbox.egg-info/requires.txt
js.jquery_expandbox.egg-info/top_level.txt
js/jquery_expandbox/__init__.py
js/jquery_expandbox/test_jquery.expandbox.txt
js/jquery_expandbox/resources/README.txt
js/jquery_expandbox/resources/jquery.expandBox.js