Metadata-Version: 1.0
Name: js.jquery-expandbox
Version: 0.2.0
Summary: Fanstatic packaging of jquery.expandBox
Home-page: UNKNOWN
Author: Stephane Klein
Author-email: stephane@harobed.org
License: BSD
Keywords: fanstatic,jquery,javascript
Platform: UNKNOWN
